spiral_cipher/__init__.py
spiral_cipher/cipher.py
spiral_cipher/cli.py
spiral_cipher-0.1.2.dist-info/METADATA
spiral_cipher-0.1.2.dist-info/WHEEL
spiral_cipher-0.1.2.dist-info/entry_points.txt
spiral_cipher-0.1.2.dist-info/top_level.txt
spiral_cipher-0.1.2.dist-info/RECORD
