Metadata-Version: 2.2
Name: spiral-cipher
Version: 0.1.2
Summary: A spiral cipher implementation for text encryption and decryption
Home-page: https://github.com/ishanoshada/spiral-cipher
Author: Ishan Oshada
Author-email: ishan.kodithuwakku.offical@gmail.com
Project-URL: Bug Tracker, https://github.com/ishanoshada/spiral-cipher/issues
Project-URL: Documentation, https://github.com/ishanoshada/spiral-cipher#readme
Project-URL: Source Code, https://github.com/ishanoshada/spiral-cipher
Keywords: cipher,encryption,spiral,cryptography,security
Platform: any
Classifier: Development Status :: 4 - Beta
Classifier: Intended Audience :: Developers
Classifier: Topic :: Security :: Cryptography
Classifier: License :: OSI Approved :: MIT License
Classifier: Programming Language :: Python :: 3
Classifier: Programming Language :: Python :: 3.6
Classifier: Programming Language :: Python :: 3.7
Classifier: Programming Language :: Python :: 3.8
Classifier: Programming Language :: Python :: 3.9
Classifier: Programming Language :: Python :: 3.10
Classifier: Programming Language :: Python :: 3.11
Classifier: Operating System :: OS Independent
Requires-Dist: typing; python_version < "3.5"
Dynamic: author
Dynamic: author-email
Dynamic: classifier
Dynamic: description
Dynamic: description-content-type
Dynamic: home-page
Dynamic: keywords
Dynamic: platform
Dynamic: project-url
Dynamic: requires-dist
Dynamic: summary
